kabomu/StandardQuasiHttpClient.py
kabomu/StandardQuasiHttpServer.py
kabomu/__init__.py
kabomu/abstractions.py
kabomu/errors.py
kabomu/io_utils_internal.py
kabomu/misc_utils_internal.py
kabomu/protocol_utils_internal.py
kabomu/quasi_http_utils.py
kabomu/tlv/__init__.py
kabomu/tlv/tlv_utils.py
kabomu-0.9.2.dist-info/LICENSE
kabomu-0.9.2.dist-info/METADATA
kabomu-0.9.2.dist-info/WHEEL
kabomu-0.9.2.dist-info/RECORD
