Metadata-Version: 2.1
Name: kabomu
Version: 0.9.2
Summary: Kabomu libary for Python
Home-page: https://github.com/aaronicsubstances/kabomu-python
License: MPL-2.0
Author: aaronicsubstances
Requires-Python: >=3.11,<4.0
Classifier: License :: OSI Approved
Classifier: Programming Language :: Python :: 3
Classifier: Programming Language :: Python :: 3.11
Classifier: Programming Language :: Python :: 3.12
Requires-Dist: trio (>=0.22.2,<0.23.0)
Project-URL: Repository, https://github.com/aaronicsubstances/kabomu-python
